jenkins_jobs/__init__.py
jenkins_jobs/exceptions.py
jenkins_jobs/exporter.py
jenkins_jobs/jobs.py
jenkins_jobs/reporter.py
jenkins_jobs/retrievers.py
jenkins_jobs-0.1.8.dist-info/licenses/AUTHORS.rst
jenkins_jobs-0.1.8.dist-info/licenses/LICENSE
jenkins_jobs-0.1.8.dist-info/METADATA
jenkins_jobs-0.1.8.dist-info/WHEEL
jenkins_jobs-0.1.8.dist-info/entry_points.txt
jenkins_jobs-0.1.8.dist-info/top_level.txt
jenkins_jobs-0.1.8.dist-info/RECORD
