Metadata-Version: 2.4
Name: jenkins_jobs
Version: 0.1.8
Summary: Listing all jobs on a Jenkins server with more information than jenkins-cli.jar
Home-page: https://github.com/glasswalk3r/jenkins-jobs
Author: Alceu Rodrigues de Freitas Junior
Author-email: glasswalk3r@yahoo.com.br
License: GNU General Public License v3
Keywords: jenkins jobs
Classifier: Development Status :: 4 - Beta
Classifier: Intended Audience :: Developers
Classifier: Intended Audience :: System Administrators
Classifier: License :: OSI Approved :: GNU General Public License v3 (GPLv3)
Classifier: Natural Language :: English
Classifier: Programming Language :: Python :: 3
Classifier: Programming Language :: Python :: 3.9
Classifier: Programming Language :: Python :: 3.10
Classifier: Programming Language :: Python :: 3.11
Classifier: Programming Language :: Python :: 3.12
Classifier: Programming Language :: Python :: 3.13
Requires-Python: >=3.9
License-File: LICENSE
License-File: AUTHORS.rst
Requires-Dist: python-jenkins>=1.7.0
Requires-Dist: xmltodict>=0.12.0
Dynamic: author
Dynamic: author-email
Dynamic: classifier
Dynamic: description
Dynamic: home-page
Dynamic: keywords
Dynamic: license
Dynamic: license-file
Dynamic: requires-dist
Dynamic: requires-python
Dynamic: summary
